topsis/__init__.py
topsis/topsis.py
Topsis_Jayant_102097013-1.1.3.dist-info/LICENSE
Topsis_Jayant_102097013-1.1.3.dist-info/METADATA
Topsis_Jayant_102097013-1.1.3.dist-info/WHEEL
Topsis_Jayant_102097013-1.1.3.dist-info/entry_points.txt
Topsis_Jayant_102097013-1.1.3.dist-info/top_level.txt
Topsis_Jayant_102097013-1.1.3.dist-info/RECORD
