Metadata-Version: 2.1
Name: Topsis-Jayant-102097013
Version: 1.1.3
Summary: API and CLI tool to calculate Topsis, CLI tool inputs CSV/Excel files
Home-page: https://github.com/jayantkatia/topsis
Author: Jayant Katia
Author-email: jayantkatia65@gmail.com
License: MIT
Download-URL: https://github.com/jayantkatia/topsis/archive/refs/tags/v1.1.3.tar.gz
Keywords: topsis,python,pypi,csv,xlsx,xls,cli
Platform: UNKNOWN
License-File: LICENSE
Requires-Dist: numpy
Requires-Dist: pandas
